src/__init__.py
src/pgp_utils.py
pgp_utils-1.0.1.dist-info/LICENSE
pgp_utils-1.0.1.dist-info/METADATA
pgp_utils-1.0.1.dist-info/WHEEL
pgp_utils-1.0.1.dist-info/entry_points.txt
pgp_utils-1.0.1.dist-info/top_level.txt
pgp_utils-1.0.1.dist-info/RECORD
