Metadata-Version: 2.1
Name: pgp-utils
Version: 1.0.1
Summary: A small utility to wrap up common pgp/yubikey operations.
Home-page: https://github.com/tdfirth/pgp-utils
Author: Tom Firth
License: UNKNOWN
Platform: UNKNOWN
Classifier: Programming Language :: Python :: 3
Classifier: License :: OSI Approved :: MIT License
Classifier: Operating System :: OS Independent
Requires-Python: >=3.6
